{
	"current_condition": [
		{
			"FeelsLikeC": "8",
			"FeelsLikeF": "46",
			"cloudcover": "75",
			"humidity": "76",
			"localObsDateTime": "2024-09-25 06:13 PM",
			"observation_time": "04:13 PM",
			"precipInches": "0.0",
			"precipMM": "0.1",
			"pressure": "1016",
			"pressureInches": "30",
			"temp_C": "9",
			"temp_F": "49",
			"uvIndex": "1",
			"visibility": "10",
			"visibilityMiles": "6",
			"weatherCode": "116",
			"weatherDesc": [
				{
					"value": "Partly cloudy"
				}
			],
			"weatherIconUrl": [
				{
					"value": ""
				}
			],
			"winddir16Point": "S",
			"winddirDegree": "191",
			"windspeedKmph": "12",
			"windspeedMiles": "7"
		}
	],
	"nearest_area": [
		{
			"areaName": [
				{
					"value": "Dosso"
				}
			],
			"country": [
				{
					"value": "Italy"
				}
			],
			"latitude": "46.450",
			"longitude": "10.217",
			"population": "47",
			"region": [
				{
					"value": "Trentino-Alto Adige"
				}
			],
			"weatherUrl": [
				{
					"value": ""
				}
			]
		}
	],
	"request": [
		{
			"query": "Lat 46.47 and Lon 10.37",
			"type": "LatLon"
		}
	],
	"weather": [
		{
			"astronomy": [
				{
					"moon_illumination": "48",
					"moon_phase": "Waning Crescent",
					"moonrise": "No moonrise",
					"moonset": "04:12 PM",
					"sunrise": "07:10 AM",
					"sunset": "07:10 PM"
				}
			],
			"avgtempC": "3",
			"avgtempF": "38",
			"date": "2024-09-25",
			"hourly": [
				{
					"DewPointC": "0",
					"DewPointF": "33",
					"FeelsLikeC": "1",
					"FeelsLikeF": "34",
					"HeatIndexC": "1",
					"HeatIndexF": "34",
					"WindChillC": "1",
					"WindChillF": "34",
					"WindGustKmph": "5",
					"WindGustMiles": "3",
					"chanceoffog": "7",
					"chanceoffrost": "10",
					"chanceofhightemp": "0",
					"chanceofovercast": "92",
					"chanceofrain": "88",
					"chanceofremdry": "0",
					"chanceofsnow": "0",
					"chanceofsunshine": "0",
					"chanceofthunder": "0",
					"chanceofwindy": "0",
					"cloudcover": "76",
					"diffRad": "0.0",
					"humidity": "95",
					"precipInches": "0.0",
					"precipMM": "0.0",
					"pressure": "1014",
					"pressureInches": "30",
					"shortRad": "0.0",
					"tempC": "1",
					"tempF": "34",
					"time": "0",
					"uvIndex": "1",
					"visibility": "2",
					"visibilityMiles": "1",
					"weatherCode": "143",
					"weatherDesc": [
						{
							"value": "Mist"
						}
					],
					"weatherIconUrl": [
						{
							"value": ""
						}
					],
					"winddir16Point": "SSW",
					"winddirDegree": "207",
					"windspeedKmph": "3",
					"windspeedMiles": "2"
				},
				{
					"DewPointC": "-0",
					"DewPointF": "32",
					"FeelsLikeC": "-0",
					"FeelsLikeF": "31",
					"HeatIndexC": "1",
					"HeatIndexF": "33",
					"WindChillC": "-0",
					"WindChillF": "31",
					"WindGustKmph": "7",
					"WindGustMiles": "4",
					"chanceoffog": "0",
					"chanceoffrost": "28",
					"chanceofhightemp": "0",
					"chanceofovercast": "92",
					"chanceofrain": "0",
					"chanceofremdry": "86",
					"chanceofsnow": "0",
					"chanceofsunshine": "19",
					"chanceofthunder": "0",
					"chanceofwindy": "0",
					"cloudcover": "43",
					"diffRad": "0.0",
					"humidity": "95",
					"precipInches": "0.0",
					"precipMM": "0.0",
					"pressure": "1014",
					"pressureInches": "30",
					"shortRad": "0.0",
					"tempC": "1",
					"tempF": "33",
					"time": "300",
					"uvIndex": "1",
					"visibility": "2",
					"visibilityMiles": "1",
					"weatherCode": "143",
					"weatherDesc": [
						{
							"value": "Mist"
						}
					],
					"weatherIconUrl": [
						{
							"value": ""
						}
					],
					"winddir16Point": "S",
					"winddirDegree": "177",
					"windspeedKmph": "4",
					"windspeedMiles": "2"
				},
				{
					"DewPointC": "-1",
					"DewPointF": "31",
					"FeelsLikeC": "-1",
					"FeelsLikeF": "30",
					"HeatIndexC": "0",
					"HeatIndexF": "32",
					"WindChillC": "-1",
					"WindChillF": "30",
					"WindGustKmph": "9",
					"WindGustMiles": "6",
					"chanceoffog": "0",
					"chanceoffrost": "39",
					"chanceofhightemp": "0",
					"chanceofovercast": "37",
					"chanceofrain": "0",
					"chanceofremdry": "90",
					"chanceofsnow": "0",
					"chanceofsunshine": "84",
					"chanceofthunder": "0",
					"chanceofwindy": "0",
					"cloudcover": "31",
					"diffRad": "0.0",
					"humidity": "93",
					"precipInches": "0.0",
					"precipMM": "0.0",
					"pressure": "1015",
					"pressureInches": "30",
					"shortRad": "0.0",
					"tempC": "0",
					"tempF": "32",
					"time": "600",
					"uvIndex": "1",
					"visibility": "10",
					"visibilityMiles": "6",
					"weatherCode": "116",
					"weatherDesc": [
						{
							"value": "Partly Cloudy "
						}
					],
					"weatherIconUrl": [
						{
							"value": ""
						}
					],
					"winddir16Point": "SSE",
					"winddirDegree": "168",
					"windspeedKmph": "5",
					"windspeedMiles": "3"
				},
				{
					"DewPointC": "1",
					"DewPointF": "34",
					"FeelsLikeC": "2",
					"FeelsLikeF": "36",
					"HeatIndexC": "4",
					"HeatIndexF": "40",
					"WindChillC": "2",
					"WindChillF": "36",
					"WindGustKmph": "10",
					"WindGustMiles": "6",
					"chanceoffog": "0",
					"chanceoffrost": "0",
					"chanceofhightemp": "0",
					"chanceofovercast": "0",
					"chanceofrain": "0",
					"chanceofremdry": "82",
					"chanceofsnow": "0",
					"chanceofsunshine": "86",
					"chanceofthunder": "0",
					"chanceofwindy": "0",
					"cloudcover": "13",
					"diffRad": "62.5",
					"humidity": "78",
					"precipInches": "0.0",
					"precipMM": "0.0",
					"pressure": "1014",
					"pressureInches": "30",
					"shortRad": "265.2",
					"tempC": "4",
					"tempF": "40",
					"time": "900",
					"uvIndex": "2",
					"visibility": "10",
					"visibilityMiles": "6",
					"weatherCode": "113",
					"weatherDesc": [
						{
							"value": "Sunny"
						}
					],
					"weatherIconUrl": [
						{
							"value": ""
						}
					],
					"winddir16Point": "S",
					"winddirDegree": "178",
					"windspeedKmph": "8",
					"windspeedMiles": "5"
				},
				{
					"DewPointC": "2",
					"DewPointF": "35",
					"FeelsLikeC": "4",
					"FeelsLikeF": "40",
					"HeatIndexC": "7",
					"HeatIndexF": "44",
					"WindChillC": "4",
					"WindChillF": "40",
					"WindGustKmph": "14",
					"WindGustMiles": "9",
					"chanceoffog": "0",
					"chanceoffrost": "0",
					"chanceofhightemp": "0",
					"chanceofovercast": "87",
					"chanceofrain": "68",
					"chanceofremdry": "0",
					"chanceofsnow": "0",
					"chanceofsunshine": "0",
					"chanceofthunder": "0",
					"chanceofwindy": "0",
					"cloudcover": "82",
					"diffRad": "121.4",
					"humidity": "71",
					"precipInches": "0.0",
					"precipMM": "0.0",
					"pressure": "1014",
					"pressureInches": "30",
					"shortRad": "430.6",
					"tempC": "7",
					"tempF": "44",
					"time": "1200",
					"uvIndex": "2",
					"visibility": "10",
					"visibilityMiles": "6",
					"weatherCode": "176",
					"weatherDesc": [
						{
							"value": "Patchy rain nearby"
						}
					],
					"weatherIconUrl": [
						{
							"value": ""
						}
					],
					"winddir16Point": "SSW",
					"winddirDegree": "196",
					"windspeedKmph": "12",
					"windspeedMiles": "7"
				},
				{
					"DewPointC": "2",
					"DewPointF": "36",
					"FeelsLikeC": "4",
					"FeelsLikeF": "40",
					"HeatIndexC": "7",
					"HeatIndexF": "44",
					"WindChillC": "4",
					"WindChillF": "40",
					"WindGustKmph": "14",
					"WindGustMiles": "9",
					"chanceoffog": "0",
					"chanceoffrost": "0",
					"chanceofhightemp": "0",
					"chanceofovercast": "82",
					"chanceofrain": "100",
					"chanceofremdry": "0",
					"chanceofsnow": "0",
					"chanceofsunshine": "0",
					"chanceofthunder": "0",
					"chanceofwindy": "0",
					"cloudcover": "72",
					"diffRad": "129.0",
					"humidity": "74",
					"precipInches": "0.0",
					"precipMM": "0.1",
					"pressure": "1013",
					"pressureInches": "30",
					"shortRad": "246.8",
					"tempC": "7",
					"tempF": "44",
					"time": "1500",
					"uvIndex": "2",
					"visibility": "10",
					"visibilityMiles": "6",
					"weatherCode": "176",
					"weatherDesc": [
						{
							"value": "Patchy rain nearby"
						}
					],
					"weatherIconUrl": [
						{
							"value": ""
						}
					],
					"winddir16Point": "SSW",
					"winddirDegree": "194",
					"windspeedKmph": "12",
					"windspeedMiles": "7"
				},
				{
					"DewPointC": "3",
					"DewPointF": "38",
					"FeelsLikeC": "1",
					"FeelsLikeF": "34",
					"HeatIndexC": "4",
					"HeatIndexF": "39",
					"WindChillC": "1",
					"WindChillF": "34",
					"WindGustKmph": "17",
					"WindGustMiles": "11",
					"chanceoffog": "0",
					"chanceoffrost": "0",
					"chanceofhightemp": "0",
					"chanceofovercast": "89",
					"chanceofrain": "100",
					"chanceofremdry": "0",
					"chanceofsnow": "0",
					"chanceofsunshine": "0",
					"chanceofthunder": "0",
					"chanceofwindy": "0",
					"cloudcover": "75",
					"diffRad": "83.6",
					"humidity": "76",
					"precipInches": "0.0",
					"precipMM": "0.1",
					"pressure": "1016",
					"pressureInches": "30",
					"shortRad": "163.0",
					"tempC": "9",
					"tempF": "49",
					"time": "1800",
					"uvIndex": "1",
					"visibility": "10",
					"visibilityMiles": "6",
					"weatherCode": "116",
					"weatherDesc": [
						{
							"value": "Partly cloudy"
						}
					],
					"weatherIconUrl": [
						{
							"value": ""
						}
					],
					"winddir16Point": "S",
					"winddirDegree": "191",
					"windspeedKmph": "12",
					"windspeedMiles": "7"
				},
				{
					"DewPointC": "2",
					"DewPointF": "36",
					"FeelsLikeC": "-0",
					"FeelsLikeF": "32",
					"HeatIndexC": "3",
					"HeatIndexF": "37",
					"WindChillC": "-0",
					"WindChillF": "32",
					"WindGustKmph": "17",
					"WindGustMiles": "11",
					"chanceoffog": "0",
					"chanceoffrost": "0",
					"chanceofhightemp": "0",
					"chanceofovercast": "91",
					"chanceofrain": "76",
					"chanceofremdry": "0",
					"chanceofsnow": "0",
					"chanceofsunshine": "0",
					"chanceofthunder": "0",
					"chanceofwindy": "0",
					"cloudcover": "92",
					"diffRad": "0.0",
					"humidity": "95",
					"precipInches": "0.0",
					"precipMM": "0.0",
					"pressure": "1015",
					"pressureInches": "30",
					"shortRad": "0.0",
					"tempC": "3",
					"tempF": "37",
					"time": "2100",
					"uvIndex": "1",
					"visibility": "2",
					"visibilityMiles": "1",
					"weatherCode": "143",
					"weatherDesc": [
						{
							"value": "Mist"
						}
					],
					"weatherIconUrl": [
						{
							"value": ""
						}
					],
					"winddir16Point": "S",
					"winddirDegree": "186",
					"windspeedKmph": "12",
					"windspeedMiles": "7"
				}
			],
			"maxtempC": "7",
			"maxtempF": "44",
			"mintempC": "0",
			"mintempF": "32",
			"sunHour": "9.8",
			"totalSnow_cm": "0.0",
			"uvIndex": "3"
		},
		{
			"astronomy": [
				{
					"moon_illumination": "37",
					"moon_phase": "Waning Crescent",
					"moonrise": "12:02 AM",
					"moonset": "04:52 PM",
					"sunrise": "07:11 AM",
					"sunset": "07:08 PM"
				}
			],
			"avgtempC": "4",
			"avgtempF": "39",
			"date": "2024-09-26",
			"hourly": [
				{
					"DewPointC": "3",
					"DewPointF": "37",
					"FeelsLikeC": "0",
					"FeelsLikeF": "32",
					"HeatIndexC": "3",
					"HeatIndexF": "38",
					"WindChillC": "0",
					"WindChillF": "32",
					"WindGustKmph": "16",
					"WindGustMiles": "10",
					"chanceoffog": "7",
					"chanceoffrost": "0",
					"chanceofhightemp": "0",
					"chanceofovercast": "84",
					"chanceofrain": "69",
					"chanceofremdry": "0",
					"chanceofsnow": "0",
					"chanceofsunshine": "0",
					"chanceofthunder": "0",
					"chanceofwindy": "0",
					"cloudcover": "85",
					"diffRad": "0.0",
					"humidity": "96",
					"precipInches": "0.0",
					"precipMM": "0.0",
					"pressure": "1013",
					"pressureInches": "30",
					"shortRad": "0.0",
					"tempC": "3",
					"tempF": "38",
					"time": "0",
					"uvIndex": "1",
					"visibility": "2",
					"visibilityMiles": "1",
					"weatherCode": "143",
					"weatherDesc": [
						{
							"value": "Mist"
						}
					],
					"weatherIconUrl": [
						{
							"value": ""
						}
					],
					"winddir16Point": "S",
					"winddirDegree": "181",
					"windspeedKmph": "12",
					"windspeedMiles": "7"
				},
				{
					"DewPointC": "2",
					"DewPointF": "36",
					"FeelsLikeC": "-0",
					"FeelsLikeF": "32",
					"HeatIndexC": "3",
					"HeatIndexF": "37",
					"WindChillC": "-0",
					"WindChillF": "32",
					"WindGustKmph": "14",
					"WindGustMiles": "9",
					"chanceoffog": "91",
					"chanceoffrost": "0",
					"chanceofhightemp": "0",
					"chanceofovercast": "88",
					"chanceofrain": "83",
					"chanceofremdry": "0",
					"chanceofsnow": "0",
					"chanceofsunshine": "0",
					"chanceofthunder": "0",
					"chanceofwindy": "0",
					"cloudcover": "100",
					"diffRad": "0.0",
					"humidity": "98",
					"precipInches": "0.0",
					"precipMM": "0.0",
					"pressure": "1013",
					"pressureInches": "30",
					"shortRad": "0.0",
					"tempC": "3",
					"tempF": "37",
					"time": "300",
					"uvIndex": "1",
					"visibility": "0",
					"visibilityMiles": "0",
					"weatherCode": "248",
					"weatherDesc": [
						{
							"value": "Fog"
						}
					],
					"weatherIconUrl": [
						{
							"value": ""
						}
					],
					"winddir16Point": "S",
					"winddirDegree": "186",
					"windspeedKmph": "10",
					"windspeedMiles": "6"
				},
				{
					"DewPointC": "2",
					"DewPointF": "36",
					"FeelsLikeC": "-1",
					"FeelsLikeF": "31",
					"HeatIndexC": "2",
					"HeatIndexF": "36",
					"WindChillC": "-1",
					"WindChillF": "31",
					"WindGustKmph": "16",
					"WindGustMiles": "10",
					"chanceoffog": "90",
					"chanceoffrost": "0",
					"chanceofhightemp": "0",
					"chanceofovercast": "86",
					"chanceofrain": "0",
					"chanceofremdry": "87",
					"chanceofsnow": "0",
					"chanceofsunshine": "14",
					"chanceofthunder": "0",
					"chanceofwindy": "0",
					"cloudcover": "100",
					"diffRad": "0.0",
					"humidity": "98",
					"precipInches": "0.0",
					"precipMM": "0.0",
					"pressure": "1012",
					"pressureInches": "30",
					"shortRad": "0.0",
					"tempC": "2",
					"tempF": "36",
					"time": "600",
					"uvIndex": "1",
					"visibility": "0",
					"visibilityMiles": "0",
					"weatherCode": "248",
					"weatherDesc": [
						{
							"value": "Fog"
						}
					],
					"weatherIconUrl": [
						{
							"value": ""
						}
					],
					"winddir16Point": "S",
					"winddirDegree": "184",
					"windspeedKmph": "11",
					"windspeedMiles": "7"
				},
				{
					"DewPointC": "3",
					"DewPointF": "37",
					"FeelsLikeC": "0",
					"FeelsLikeF": "33",
					"HeatIndexC": "4",
					"HeatIndexF": "38",
					"WindChillC": "0",
					"WindChillF": "33",
					"WindGustKmph": "16",
					"WindGustMiles": "10",
					"chanceoffog": "0",
					"chanceoffrost": "0",
					"chanceofhightemp": "0",
					"chanceofovercast": "86",
					"chanceofrain": "81",
					"chanceofremdry": "0",
					"chanceofsnow": "0",
					"chanceofsunshine": "0",
					"chanceofthunder": "0",
					"chanceofwindy": "0",
					"cloudcover": "87",
					"diffRad": "32.5",
					"humidity": "94",
					"precipInches": "0.0",
					"precipMM": "0.0",
					"pressure": "1013",
					"pressureInches": "30",
					"shortRad": "57.6",
					"tempC": "4",
					"tempF": "38",
					"time": "900",
					"uvIndex": "1",
					"visibility": "10",
					"visibilityMiles": "6",
					"weatherCode": "176",
					"weatherDesc": [
						{
							"value": "Patchy rain nearby"
						}
					],
					"weatherIconUrl": [
						{
							"value": ""
						}
					],
					"winddir16Point": "S",
					"winddirDegree": "189",
					"windspeedKmph": "13",
					"windspeedMiles": "8"
				},
				{
					"DewPointC": "4",
					"DewPointF": "39",
					"FeelsLikeC": "2",
					"FeelsLikeF": "35",
					"HeatIndexC": "5",
					"HeatIndexF": "41",
					"WindChillC": "2",
					"WindChillF": "35",
					"WindGustKmph": "17",
					"WindGustMiles": "10",
					"chanceoffog": "0",
					"chanceoffrost": "0",
					"chanceofhightemp": "0",
					"chanceofovercast": "85",
					"chanceofrain": "74",
					"chanceofremdry": "0",
					"chanceofsnow": "0",
					"chanceofsunshine": "0",
					"chanceofthunder": "0",
					"chanceofwindy": "0",
					"cloudcover": "100",
					"diffRad": "40.8",
					"humidity": "96",
					"precipInches": "0.0",
					"precipMM": "0.0",
					"pressure": "1012",
					"pressureInches": "30",
					"shortRad": "69.2",
					"tempC": "5",
					"tempF": "41",
					"time": "1200",
					"uvIndex": "1",
					"visibility": "10",
					"visibilityMiles": "6",
					"weatherCode": "176",
					"weatherDesc": [
						{
							"value": "Patchy rain nearby"
						}
					],
					"weatherIconUrl": [
						{
							"value": ""
						}
					],
					"winddir16Point": "SSW",
					"winddirDegree": "191",
					"windspeedKmph": "13",
					"windspeedMiles": "8"
				},
				{
					"DewPointC": "4",
					"DewPointF": "40",
					"FeelsLikeC": "2",
					"FeelsLikeF": "35",
					"HeatIndexC": "5",
					"HeatIndexF": "40",
					"WindChillC": "2",
					"WindChillF": "35",
					"WindGustKmph": "19",
					"WindGustMiles": "12",
					"chanceoffog": "4",
					"chanceoffrost": "0",
					"chanceofhightemp": "0",
					"chanceofovercast": "83",
					"chanceofrain": "100",
					"chanceofremdry": "0",
					"chanceofsnow": "0",
					"chanceofsunshine": "0",
					"chanceofthunder": "0",
					"chanceofwindy": "0",
					"cloudcover": "100",
					"diffRad": "11.1",
					"humidity": "98",
					"precipInches": "0.0",
					"precipMM": "0.3",
					"pressure": "1010",
					"pressureInches": "30",
					"shortRad": "14.6",
					"tempC": "5",
					"tempF": "40",
					"time": "1500",
					"uvIndex": "1",
					"visibility": "2",
					"visibilityMiles": "1",
					"weatherCode": "266",
					"weatherDesc": [
						{
							"value": "Light drizzle"
						}
					],
					"weatherIconUrl": [
						{
							"value": ""
						}
					],
					"winddir16Point": "S",
					"winddirDegree": "182",
					"windspeedKmph": "12",
					"windspeedMiles": "8"
				},
				{
					"DewPointC": "5",
					"DewPointF": "41",
					"FeelsLikeC": "2",
					"FeelsLikeF": "36",
					"HeatIndexC": "5",
					"HeatIndexF": "41",
					"WindChillC": "2",
					"WindChillF": "36",
					"WindGustKmph": "19",
					"WindGustMiles": "12",
					"chanceoffog": "0",
					"chanceoffrost": "0",
					"chanceofhightemp": "0",
					"chanceofovercast": "92",
					"chanceofrain": "100",
					"chanceofremdry": "0",
					"chanceofsnow": "0",
					"chanceofsunshine": "0",
					"chanceofthunder": "0",
					"chanceofwindy": "0",
					"cloudcover": "100",
					"diffRad": "6.8",
					"humidity": "98",
					"precipInches": "0.0",
					"precipMM": "0.5",
					"pressure": "1008",
					"pressureInches": "30",
					"shortRad": "8.9",
					"tempC": "5",
					"tempF": "41",
					"time": "1800",
					"uvIndex": "2",
					"visibility": "2",
					"visibilityMiles": "1",
					"weatherCode": "266",
					"weatherDesc": [
						{
							"value": "Light drizzle"
						}
					],
					"weatherIconUrl": [
						{
							"value": ""
						}
					],
					"winddir16Point": "S",
					"winddirDegree": "177",
					"windspeedKmph": "12",
					"windspeedMiles": "7"
				},
				{
					"DewPointC": "5",
					"DewPointF": "42",
					"FeelsLikeC": "3",
					"FeelsLikeF": "38",
					"HeatIndexC": "6",
					"HeatIndexF": "42",
					"WindChillC": "3",
					"WindChillF": "38",
					"WindGustKmph": "18",
					"WindGustMiles": "11",
					"chanceoffog": "0",
					"chanceoffrost": "0",
					"chanceofhightemp": "0",
					"chanceofovercast": "80",
					"chanceofrain": "100",
					"chanceofremdry": "0",
					"chanceofsnow": "0",
					"chanceofsunshine": "0",
					"chanceofthunder": "0",
					"chanceofwindy": "0",
					"cloudcover": "100",
					"diffRad": "0.0",
					"humidity": "99",
					"precipInches": "0.0",
					"precipMM": "1.1",
					"pressure": "1007",
					"pressureInches": "30",
					"shortRad": "0.0",
					"tempC": "6",
					"tempF": "42",
					"time": "2100",
					"uvIndex": "1",
					"visibility": "9",
					"visibilityMiles": "5",
					"weatherCode": "296",
					"weatherDesc": [
						{
							"value": "Light rain"
						}
					],
					"weatherIconUrl": [
						{
							"value": ""
						}
					],
					"winddir16Point": "S",
					"winddirDegree": "179",
					"windspeedKmph": "11",
					"windspeedMiles": "7"
				}
			],
			"maxtempC": "5",
			"maxtempF": "41",
			"mintempC": "2",
			"mintempF": "36",
			"sunHour": "9.0",
			"totalSnow_cm": "0.0",
			"uvIndex": "2"
		},
		{
			"astronomy": [
				{
					"moon_illumination": "28",
					"moon_phase": "Waning Crescent",
					"moonrise": "01:12 AM",
					"moonset": "05:22 PM",
					"sunrise": "07:12 AM",
					"sunset": "07:06 PM"
				}
			],
			"avgtempC": "6",
			"avgtempF": "42",
			"date": "2024-09-27",
			"hourly": [
				{
					"DewPointC": "6",
					"DewPointF": "42",
					"FeelsLikeC": "6",
					"FeelsLikeF": "42",
					"HeatIndexC": "6",
					"HeatIndexF": "42",
					"WindChillC": "6",
					"WindChillF": "42",
					"WindGustKmph": "3",
					"WindGustMiles": "2",
					"chanceoffog": "0",
					"chanceoffrost": "0",
					"chanceofhightemp": "0",
					"chanceofovercast": "93",
					"chanceofrain": "100",
					"chanceofremdry": "0",
					"chanceofsnow": "0",
					"chanceofsunshine": "0",
					"chanceofthunder": "0",
					"chanceofwindy": "0",
					"cloudcover": "100",
					"diffRad": "0.0",
					"humidity": "99",
					"precipInches": "0.1",
					"precipMM": "3.7",
					"pressure": "1007",
					"pressureInches": "30",
					"shortRad": "0.0",
					"tempC": "6",
					"tempF": "42",
					"time": "0",
					"uvIndex": "1",
					"visibility": "7",
					"visibilityMiles": "4",
					"weatherCode": "302",
					"weatherDesc": [
						{
							"value": "Moderate rain"
						}
					],
					"weatherIconUrl": [
						{
							"value": ""
						}
					],
					"winddir16Point": "NNW",
					"winddirDegree": "333",
					"windspeedKmph": "2",
					"windspeedMiles": "1"
				},
				{
					"DewPointC": "5",
					"DewPointF": "41",
					"FeelsLikeC": "5",
					"FeelsLikeF": "41",
					"HeatIndexC": "5",
					"HeatIndexF": "41",
					"WindChillC": "5",
					"WindChillF": "41",
					"WindGustKmph": "3",
					"WindGustMiles": "2",
					"chanceoffog": "0",
					"chanceoffrost": "0",
					"chanceofhightemp": "0",
					"chanceofovercast": "80",
					"chanceofrain": "100",
					"chanceofremdry": "0",
					"chanceofsnow": "0",
					"chanceofsunshine": "0",
					"chanceofthunder": "0",
					"chanceofwindy": "0",
					"cloudcover": "100",
					"diffRad": "0.0",
					"humidity": "99",
					"precipInches": "0.1",
					"precipMM": "3.4",
					"pressure": "1007",
					"pressureInches": "30",
					"shortRad": "0.0",
					"tempC": "5",
					"tempF": "41",
					"time": "300",
					"uvIndex": "1",
					"visibility": "7",
					"visibilityMiles": "4",
					"weatherCode": "302",
					"weatherDesc": [
						{
							"value": "Moderate rain"
						}
					],
					"weatherIconUrl": [
						{
							"value": ""
						}
					],
					"winddir16Point": "WNW",
					"winddirDegree": "284",
					"windspeedKmph": "2",
					"windspeedMiles": "1"
				},
				{
					"DewPointC": "5",
					"DewPointF": "41",
					"FeelsLikeC": "5",
					"FeelsLikeF": "42",
					"HeatIndexC": "5",
					"HeatIndexF": "42",
					"WindChillC": "5",
					"WindChillF": "42",
					"WindGustKmph": "4",
					"WindGustMiles": "3",
					"chanceoffog": "0",
					"chanceoffrost": "0",
					"chanceofhightemp": "0",
					"chanceofovercast": "90",
					"chanceofrain": "100",
					"chanceofremdry": "0",
					"chanceofsnow": "0",
					"chanceofsunshine": "0",
					"chanceofthunder": "0",
					"chanceofwindy": "0",
					"cloudcover": "100",
					"diffRad": "0.0",
					"humidity": "99",
					"precipInches": "0.1",
					"precipMM": "3.7",
					"pressure": "1006",
					"pressureInches": "30",
					"shortRad": "0.0",
					"tempC": "5",
					"tempF": "42",
					"time": "600",
					"uvIndex": "1",
					"visibility": "7",
					"visibilityMiles": "4",
					"weatherCode": "302",
					"weatherDesc": [
						{
							"value": "Moderate rain"
						}
					],
					"weatherIconUrl": [
						{
							"value": ""
						}
					],
					"winddir16Point": "W",
					"winddirDegree": "259",
					"windspeedKmph": "3",
					"windspeedMiles": "2"
				},
				{
					"DewPointC": "6",
					"DewPointF": "43",
					"FeelsLikeC": "4",
					"FeelsLikeF": "40",
					"HeatIndexC": "6",
					"HeatIndexF": "44",
					"WindChillC": "4",
					"WindChillF": "40",
					"WindGustKmph": "16",
					"WindGustMiles": "10",
					"chanceoffog": "0",
					"chanceoffrost": "0",
					"chanceofhightemp": "0",
					"chanceofovercast": "87",
					"chanceofrain": "100",
					"chanceofremdry": "0",
					"chanceofsnow": "0",
					"chanceofsunshine": "0",
					"chanceofthunder": "0",
					"chanceofwindy": "0",
					"cloudcover": "100",
					"diffRad": "5.7",
					"humidity": "99",
					"precipInches": "0.0",
					"precipMM": "0.6",
					"pressure": "1008",
					"pressureInches": "30",
					"shortRad": "8.0",
					"tempC": "6",
					"tempF": "44",
					"time": "900",
					"uvIndex": "2",
					"visibility": "10",
					"visibilityMiles": "6",
					"weatherCode": "353",
					"weatherDesc": [
						{
							"value": "Light rain shower"
						}
					],
					"weatherIconUrl": [
						{
							"value": ""
						}
					],
					"winddir16Point": "S",
					"winddirDegree": "181",
					"windspeedKmph": "11",
					"windspeedMiles": "7"
				},
				{
					"DewPointC": "7",
					"DewPointF": "44",
					"FeelsLikeC": "5",
					"FeelsLikeF": "41",
					"HeatIndexC": "8",
					"HeatIndexF": "46",
					"WindChillC": "5",
					"WindChillF": "41",
					"WindGustKmph": "20",
					"WindGustMiles": "12",
					"chanceoffog": "0",
					"chanceoffrost": "0",
					"chanceofhightemp": "0",
					"chanceofovercast": "92",
					"chanceofrain": "100",
					"chanceofremdry": "0",
					"chanceofsnow": "0",
					"chanceofsunshine": "0",
					"chanceofthunder": "80",
					"chanceofwindy": "0",
					"cloudcover": "58",
					"diffRad": "35.7",
					"humidity": "92",
					"precipInches": "0.0",
					"precipMM": "0.3",
					"pressure": "1007",
					"pressureInches": "30",
					"shortRad": "61.7",
					"tempC": "8",
					"tempF": "46",
					"time": "1200",
					"uvIndex": "2",
					"visibility": "10",
					"visibilityMiles": "6",
					"weatherCode": "353",
					"weatherDesc": [
						{
							"value": "Light rain shower"
						}
					],
					"weatherIconUrl": [
						{
							"value": ""
						}
					],
					"winddir16Point": "S",
					"winddirDegree": "181",
					"windspeedKmph": "15",
					"windspeedMiles": "9"
				},
				{
					"DewPointC": "6",
					"DewPointF": "43",
					"FeelsLikeC": "4",
					"FeelsLikeF": "39",
					"HeatIndexC": "7",
					"HeatIndexF": "44",
					"WindChillC": "4",
					"WindChillF": "39",
					"WindGustKmph": "18",
					"WindGustMiles": "11",
					"chanceoffog": "0",
					"chanceoffrost": "0",
					"chanceofhightemp": "0",
					"chanceofovercast": "82",
					"chanceofrain": "100",
					"chanceofremdry": "0",
					"chanceofsnow": "0",
					"chanceofsunshine": "0",
					"chanceofthunder": "78",
					"chanceofwindy": "0",
					"cloudcover": "70",
					"diffRad": "27.9",
					"humidity": "95",
					"precipInches": "0.0",
					"precipMM": "0.4",
					"pressure": "1007",
					"pressureInches": "30",
					"shortRad": "43.4",
					"tempC": "7",
					"tempF": "44",
					"time": "1500",
					"uvIndex": "2",
					"visibility": "5",
					"visibilityMiles": "3",
					"weatherCode": "263",
					"weatherDesc": [
						{
							"value": "Patchy light drizzle"
						}
					],
					"weatherIconUrl": [
						{
							"value": ""
						}
					],
					"winddir16Point": "S",
					"winddirDegree": "183",
					"windspeedKmph": "14",
					"windspeedMiles": "9"
				},
				{
					"DewPointC": "5",
					"DewPointF": "40",
					"FeelsLikeC": "3",
					"FeelsLikeF": "37",
					"HeatIndexC": "5",
					"HeatIndexF": "41",
					"WindChillC": "3",
					"WindChillF": "37",
					"WindGustKmph": "18",
					"WindGustMiles": "11",
					"chanceoffog": "0",
					"chanceoffrost": "0",
					"chanceofhightemp": "0",
					"chanceofovercast": "82",
					"chanceofrain": "100",
					"chanceofremdry": "0",
					"chanceofsnow": "0",
					"chanceofsunshine": "0",
					"chanceofthunder": "58",
					"chanceofwindy": "0",
					"cloudcover": "72",
					"diffRad": "29.3",
					"humidity": "96",
					"precipInches": "0.0",
					"precipMM": "0.2",
					"pressure": "1007",
					"pressureInches": "30",
					"shortRad": "51.0",
					"tempC": "5",
					"tempF": "41",
					"time": "1800",
					"uvIndex": "2",
					"visibility": "10",
					"visibilityMiles": "6",
					"weatherCode": "353",
					"weatherDesc": [
						{
							"value": "Light rain shower"
						}
					],
					"weatherIconUrl": [
						{
							"value": ""
						}
					],
					"winddir16Point": "S",
					"winddirDegree": "178",
					"windspeedKmph": "12",
					"windspeedMiles": "7"
				},
				{
					"DewPointC": "3",
					"DewPointF": "38",
					"FeelsLikeC": "1",
					"FeelsLikeF": "34",
					"HeatIndexC": "4",
					"HeatIndexF": "39",
					"WindChillC": "1",
					"WindChillF": "34",
					"WindGustKmph": "17",
					"WindGustMiles": "10",
					"chanceoffog": "1",
					"chanceoffrost": "0",
					"chanceofhightemp": "0",
					"chanceofovercast": "85",
					"chanceofrain": "100",
					"chanceofremdry": "0",
					"chanceofsnow": "0",
					"chanceofsunshine": "0",
					"chanceofthunder": "56",
					"chanceofwindy": "0",
					"cloudcover": "75",
					"diffRad": "0.0",
					"humidity": "96",
					"precipInches": "0.0",
					"precipMM": "0.2",
					"pressure": "1008",
					"pressureInches": "30",
					"shortRad": "0.0",
					"tempC": "4",
					"tempF": "39",
					"time": "2100",
					"uvIndex": "1",
					"visibility": "5",
					"visibilityMiles": "3",
					"weatherCode": "263",
					"weatherDesc": [
						{
							"value": "Patchy light drizzle"
						}
					],
					"weatherIconUrl": [
						{
							"value": ""
						}
					],
					"winddir16Point": "SSE",
					"winddirDegree": "168",
					"windspeedKmph": "11",
					"windspeedMiles": "7"
				}
			],
			"maxtempC": "8",
			"maxtempF": "46",
			"mintempC": "4",
			"mintempF": "39",
			"sunHour": "9.3",
			"totalSnow_cm": "0.0",
			"uvIndex": "2"
		}
	]
}